swan_mcs/__init__.py
swan_mcs/api_client.py
swan_mcs/api/__init__.py
swan_mcs/api/bucket_api.py
swan_mcs/common/__init__.py
swan_mcs/common/constants.py
swan_mcs/common/exceptions.py
swan_mcs/common/params.py
swan_mcs/common/utils.py
swan_mcs/contract/__init__.py
swan_mcs/object/bucket_storage.py
swan_mcs/object/onchain_storage.py
python_mcs_sdk-0.3.2.dist-info/LICENSE
python_mcs_sdk-0.3.2.dist-info/METADATA
python_mcs_sdk-0.3.2.dist-info/WHEEL
python_mcs_sdk-0.3.2.dist-info/top_level.txt
python_mcs_sdk-0.3.2.dist-info/RECORD
