Metadata-Version: 2.1
Name: python-mcs-sdk
Version: 0.3.2
Summary: A python software development kit for the Multi-Chain Storage
Author: daniel8088
Author-email: danilew8088@gmail.com
License: MIT
License-File: LICENSE
Requires-Dist: web3 (==5.31.1)
Requires-Dist: requests (==2.28.1)
Requires-Dist: requests-toolbelt (==0.10.1)
Requires-Dist: tqdm (==4.64.1)
